{
    "version": "https://jsonfeed.org/version/1",
    "title": "blog",
    "subtitle": "",
    "icon": "https://stoic-yang.github.io/images/favicon.ico",
    "description": "",
    "home_page_url": "https://stoic-yang.github.io",
    "items": [
        {
            "id": "https://stoic-yang.github.io/2024/12/12/%E4%BA%8C%E5%88%86%E6%9F%A5%E6%89%BE/",
            "url": "https://stoic-yang.github.io/2024/12/12/%E4%BA%8C%E5%88%86%E6%9F%A5%E6%89%BE/",
            "title": "二分查找",
            "date_published": "2024-12-12T05:38:01.000Z",
            "content_html": "<h2 id=\"二分查找\"><a class=\"anchor\" href=\"#二分查找\">#</a> 二分查找</h2>\n<p><span class=\"exturl\" data-url=\"aHR0cHM6Ly9wcm9ncmFtbWVyY2FybC5jb20vMDcwNC4lRTQlQkElOEMlRTUlODglODYlRTYlOUYlQTUlRTYlODklQkUuaHRtbCMlRTYlODAlOUQlRTglQjclQUY=\">二分查找讲解</span><br />\n <figure class=\"highlight java\"><table><tr><td class=\"gutter\"><pre><span class=\"line\">1</span><br><span class=\"line\">2</span><br><span class=\"line\">3</span><br><span class=\"line\">4</span><br><span class=\"line\">5</span><br><span class=\"line\">6</span><br><span class=\"line\">7</span><br><span class=\"line\">8</span><br><span class=\"line\">9</span><br><span class=\"line\">10</span><br><span class=\"line\">11</span><br><span class=\"line\">12</span><br><span class=\"line\">13</span><br><span class=\"line\">14</span><br><span class=\"line\">15</span><br><span class=\"line\">16</span><br><span class=\"line\">17</span><br><span class=\"line\">18</span><br><span class=\"line\">19</span><br></pre></td><td class=\"code\"><pre><span class=\"line\"><span class=\"comment\">// 版本一</span></span><br><span class=\"line\"><span class=\"keyword\">class</span> <span class=\"title class_\">Solution</span> &#123;</span><br><span class=\"line\"><span class=\"keyword\">public</span>:</span><br><span class=\"line\">    <span class=\"type\">int</span> <span class=\"title function_\">search</span><span class=\"params\">(vector&lt;<span class=\"type\">int</span>&gt;&amp; nums, <span class=\"type\">int</span> target)</span> &#123;</span><br><span class=\"line\">        <span class=\"type\">int</span> <span class=\"variable\">left</span> <span class=\"operator\">=</span> <span class=\"number\">0</span>;</span><br><span class=\"line\">        <span class=\"type\">int</span> <span class=\"variable\">right</span> <span class=\"operator\">=</span> nums.size() - <span class=\"number\">1</span>; </span><br><span class=\"line\">        <span class=\"keyword\">while</span> (left &lt;= right) &#123; </span><br><span class=\"line\">            <span class=\"type\">int</span> <span class=\"variable\">middle</span> <span class=\"operator\">=</span> left + ((right - left) / <span class=\"number\">2</span>);</span><br><span class=\"line\">            <span class=\"keyword\">if</span> (nums[middle] &gt; target) &#123;</span><br><span class=\"line\">                right = middle - <span class=\"number\">1</span>; </span><br><span class=\"line\">            &#125; <span class=\"keyword\">else</span> <span class=\"keyword\">if</span> (nums[middle] &lt; target) &#123;</span><br><span class=\"line\">                left = middle + <span class=\"number\">1</span>; </span><br><span class=\"line\">            &#125; <span class=\"keyword\">else</span> &#123;</span><br><span class=\"line\">                <span class=\"keyword\">return</span> middle; </span><br><span class=\"line\">            &#125;</span><br><span class=\"line\">        &#125;</span><br><span class=\"line\">        <span class=\"keyword\">return</span> -<span class=\"number\">1</span>;</span><br><span class=\"line\">    &#125;</span><br><span class=\"line\">&#125;;</span><br></pre></td></tr></table></figure><br />\n<span class=\"exturl\" data-url=\"aHR0cHM6Ly9sZWV0Y29kZS5jbi9wcm9ibGVtcy9maW5kLWZpcnN0LWFuZC1sYXN0LXBvc2l0aW9uLW9mLWVsZW1lbnQtaW4tc29ydGVkLWFycmF5Lw==\">34</span><br />\n<figure class=\"highlight java\"><table><tr><td class=\"gutter\"><pre><span class=\"line\">1</span><br><span class=\"line\">2</span><br><span class=\"line\">3</span><br><span class=\"line\">4</span><br><span class=\"line\">5</span><br><span class=\"line\">6</span><br><span class=\"line\">7</span><br><span class=\"line\">8</span><br><span class=\"line\">9</span><br><span class=\"line\">10</span><br><span class=\"line\">11</span><br><span class=\"line\">12</span><br><span class=\"line\">13</span><br><span class=\"line\">14</span><br><span class=\"line\">15</span><br><span class=\"line\">16</span><br><span class=\"line\">17</span><br><span class=\"line\">18</span><br><span class=\"line\">19</span><br><span class=\"line\">20</span><br><span class=\"line\">21</span><br><span class=\"line\">22</span><br><span class=\"line\">23</span><br><span class=\"line\">24</span><br></pre></td><td class=\"code\"><pre><span class=\"line\"><span class=\"keyword\">class</span> <span class=\"title class_\">Solution</span> &#123;</span><br><span class=\"line\">    <span class=\"keyword\">public</span> <span class=\"type\">int</span>[] searchRange(<span class=\"type\">int</span>[] nums, <span class=\"type\">int</span> target) &#123;</span><br><span class=\"line\">        <span class=\"type\">int</span> <span class=\"variable\">start</span> <span class=\"operator\">=</span> heper(nums, target);</span><br><span class=\"line\">        <span class=\"keyword\">if</span> (start == nums.length || nums[start] != target) &#123;</span><br><span class=\"line\">            <span class=\"keyword\">return</span> <span class=\"keyword\">new</span> <span class=\"title class_\">int</span>[] &#123;-<span class=\"number\">1</span>, -<span class=\"number\">1</span>&#125;;</span><br><span class=\"line\">        &#125;</span><br><span class=\"line\">        <span class=\"type\">int</span> <span class=\"variable\">end</span> <span class=\"operator\">=</span> heper(nums, target + <span class=\"number\">1</span>) - <span class=\"number\">1</span>;</span><br><span class=\"line\">        <span class=\"keyword\">return</span> <span class=\"keyword\">new</span> <span class=\"title class_\">int</span>[]&#123;start, end&#125;;<span class=\"comment\">// 简单的创建一个新的数组的方式,[start, end]</span></span><br><span class=\"line\">    &#125;</span><br><span class=\"line\"></span><br><span class=\"line\">    <span class=\"keyword\">public</span> <span class=\"keyword\">static</span> <span class=\"type\">int</span> <span class=\"title function_\">heper</span><span class=\"params\">(<span class=\"type\">int</span>[] nums, <span class=\"type\">int</span> target)</span> &#123;</span><br><span class=\"line\">        <span class=\"type\">int</span> <span class=\"variable\">left</span> <span class=\"operator\">=</span> <span class=\"number\">0</span>;</span><br><span class=\"line\">        <span class=\"type\">int</span> <span class=\"variable\">right</span> <span class=\"operator\">=</span> nums.length - <span class=\"number\">1</span>;</span><br><span class=\"line\">        <span class=\"keyword\">while</span> (left &lt;= right) &#123;</span><br><span class=\"line\">            <span class=\"type\">int</span> <span class=\"variable\">mid</span> <span class=\"operator\">=</span> left + (right - left) / <span class=\"number\">2</span>;</span><br><span class=\"line\">            <span class=\"keyword\">if</span> (nums[mid] &gt;= target) &#123;</span><br><span class=\"line\">                right = mid - <span class=\"number\">1</span>;</span><br><span class=\"line\">            &#125; <span class=\"keyword\">else</span> &#123;</span><br><span class=\"line\">                left = mid + <span class=\"number\">1</span>;</span><br><span class=\"line\">            &#125;</span><br><span class=\"line\">        &#125;</span><br><span class=\"line\">        <span class=\"keyword\">return</span> left;</span><br><span class=\"line\">    &#125;</span><br><span class=\"line\">&#125;</span><br></pre></td></tr></table></figure></p>\n<h2 id=\"以后采用的版本左右开区间\"><a class=\"anchor\" href=\"#以后采用的版本左右开区间\">#</a> 以后采用的版本，左右开区间</h2>\n<p><figure class=\"highlight java\"><table><tr><td class=\"gutter\"><pre><span class=\"line\">1</span><br><span class=\"line\">2</span><br><span class=\"line\">3</span><br><span class=\"line\">4</span><br><span class=\"line\">5</span><br><span class=\"line\">6</span><br><span class=\"line\">7</span><br><span class=\"line\">8</span><br><span class=\"line\">9</span><br><span class=\"line\">10</span><br><span class=\"line\">11</span><br><span class=\"line\">12</span><br></pre></td><td class=\"code\"><pre><span class=\"line\"><span class=\"keyword\">private</span> <span class=\"type\">char</span> <span class=\"title function_\">binarySearch</span><span class=\"params\">(<span class=\"type\">char</span>[] letters, <span class=\"type\">char</span> target)</span> &#123;</span><br><span class=\"line\">        <span class=\"type\">int</span> <span class=\"variable\">left</span> <span class=\"operator\">=</span> -<span class=\"number\">1</span>, right = letters.length; <span class=\"comment\">// (left, right)</span></span><br><span class=\"line\">        <span class=\"keyword\">while</span>(left + <span class=\"number\">1</span> &lt; right) &#123; </span><br><span class=\"line\">            <span class=\"type\">int</span> <span class=\"variable\">mid</span> <span class=\"operator\">=</span> left + (right - left) / <span class=\"number\">2</span>;</span><br><span class=\"line\">            <span class=\"keyword\">if</span>(letters[mid] &lt; target) &#123;</span><br><span class=\"line\">                left = mid;</span><br><span class=\"line\">            &#125;<span class=\"keyword\">else</span> &#123;</span><br><span class=\"line\">                right = mid;</span><br><span class=\"line\">            &#125;</span><br><span class=\"line\">        &#125;</span><br><span class=\"line\">        <span class=\"keyword\">return</span> letters[right];</span><br><span class=\"line\">    &#125;</span><br></pre></td></tr></table></figure></p>\n<ol>\n<li>while 循环里面的 condition 是 left + 1 &lt; right</li>\n<li>更新左右区间都是 right or left = mid</li>\n<li>返回 right</li>\n</ol>\n<h2 id=\"不同类型统一化处理\"><a class=\"anchor\" href=\"#不同类型统一化处理\">#</a> 不同类型统一化处理</h2>\n<p>以上是处理 &gt;= 的情况<br />\n<img data-src=\"assets/1.png\" alt=\"示意图\" /><br />\n<img data-src=\"assets/2.png\" alt=\"示意图\" /><br />\n<em>就是对应这个图里面的 right 和 left 找区间</em></p>\n<p><em>最关键的是区间外是什么范围</em></p>\n",
            "tags": [
                "算法",
                "leetcode",
                "算法"
            ]
        },
        {
            "id": "https://stoic-yang.github.io/2024/11/16/%E9%9A%8F%E7%AC%942024-11-15/",
            "url": "https://stoic-yang.github.io/2024/11/16/%E9%9A%8F%E7%AC%942024-11-15/",
            "title": "随笔2024-11-15",
            "date_published": "2024-11-15T16:26:47.000Z",
            "content_html": "",
            "tags": []
        },
        {
            "id": "https://stoic-yang.github.io/2024/11/08/2024-11-8/",
            "url": "https://stoic-yang.github.io/2024/11/08/2024-11-8/",
            "title": "2024-11-8",
            "date_published": "2024-11-08T15:44:42.000Z",
            "content_html": "<p>今天看了一下华师大的插班生信息，本来抱有很大希望的，现在只当是抽奖机会了，可以用来做支线，不能 all in 华师大软工，打算借这个机会精进一下高数，万一以后打算考研，这个就有很好的基础了，还有就是英语阅读，达到考研的难度，我可以开始准备一下考研和四六级的词汇，总的来说，只要我不报班，我就是稳赢的。</p>\n<p>今天下午的时候去吃了 KFC，好贵，没有吃饱，把盘子端到面前的时候突然想起了在上小学的时候，我心娇，每次去汝城的时候都要拉着老爸去吃一次肯德基，大概是想让老爸多留在自己身边一会吧，现在一个人吃 KFC，突然就有点酸了，那个时候真好呀，真让人怀念，cry。</p>\n<p>晚上就比较糟糕了，没有能够持续学习，而且因为下午没吃饱，晚上去吃夜宵了，于是就耽误了两个小时的学习时间。</p>\n",
            "tags": [
                "打卡"
            ]
        },
        {
            "id": "https://stoic-yang.github.io/2024/11/07/2024-11-7/",
            "url": "https://stoic-yang.github.io/2024/11/07/2024-11-7/",
            "title": "2024-11-7",
            "date_published": "2024-11-07T14:20:30.000Z",
            "content_html": "<p>今天考完了思道法，接下来是接近一周的假期，最后到晚上的时候失控的预兆就出现了，刷了刷 Q 群，发现自己对计算机就业还有各个领域都认识浅薄，而且发现自己现在真的很幼稚愚蠢，还好，现在有了博客，可以不用把内容放在动态里面了，动态就只是发记录就行了，还有计划。</p>\n<p>世界真的是复杂呀，远比我想象的要复杂，我现在要不要赶紧跑路？计算机的水好深，现在感觉自己像一个白痴，不能再随便发动态了，不然要羞耻退网了，多刷刷 Q 群还是可以长长见识的，多冲浪自己才能成熟。</p>\n",
            "tags": [
                "打卡"
            ]
        },
        {
            "id": "https://stoic-yang.github.io/2024/11/07/%E6%88%91%E7%9A%84%E5%8D%9A%E5%AE%A2%E7%BD%91%E7%AB%99%E6%90%AD%E5%BB%BA%E7%9A%84%E7%BB%8F%E9%AA%8C/",
            "url": "https://stoic-yang.github.io/2024/11/07/%E6%88%91%E7%9A%84%E5%8D%9A%E5%AE%A2%E7%BD%91%E7%AB%99%E6%90%AD%E5%BB%BA%E7%9A%84%E7%BB%8F%E9%AA%8C/",
            "title": "我的博客网站搭建的经验",
            "date_published": "2024-11-07T11:11:51.000Z",
            "content_html": "<h2 id=\"我的博客情况\"><a class=\"anchor\" href=\"#我的博客情况\">#</a> 我的博客情况</h2>\n<p>我的博客是基于 hexo 和 GitHubpages 搭建的，没有弄域名，<s>因为懒</s>，</p>\n",
            "tags": [
                "网站",
                "网站"
            ]
        },
        {
            "id": "https://stoic-yang.github.io/2024/11/04/%E6%88%91%E4%B8%BA%E4%BB%80%E4%B9%88%E8%A6%81%E6%90%AD%E5%BB%BA%E4%B8%AA%E4%BA%BA%E5%8D%9A%E5%AE%A2%EF%BC%9F/",
            "url": "https://stoic-yang.github.io/2024/11/04/%E6%88%91%E4%B8%BA%E4%BB%80%E4%B9%88%E8%A6%81%E6%90%AD%E5%BB%BA%E4%B8%AA%E4%BA%BA%E5%8D%9A%E5%AE%A2%EF%BC%9F/",
            "title": "我为什么要搭建个人博客？",
            "date_published": "2024-11-04T11:06:00.000Z",
            "content_html": "<p>个人博客其实只是为了给我一个极其私密的空间，让我可以自由自在地发表我的想法和记录我的生活，其实我没有想到有一天我更加喜欢互联网，而不是现实世界，进入大学以来孤独已经成为了我的常态，但现实是我的真实的想法，我的愿景与志向无处与朋友亲人诉说，我的苦闷与孤独有时也无法排解，所有我一个没有写日记习惯的人，现在每天晚上都有着强烈的欲望写点东西，话不能憋着，我也不想去现实里面或者我的 QQ 动态里面嗷嗷大叫，这样我觉得不妥，也可能会无意伤害到别人，所以我转移阵地到这里，不在现实我的人际中公开，也许只是写给我一个人看。</p>\n<p>我也不知道什么时候我变成了一个喜欢捣鼓的人。以前我总是嫌麻烦，很懒，喜欢简单容易做的事情，现在竟然会愿意自己捣鼓一个网站，其实借助平台也是可以做到这样的。玩一玩这些 hexo、hugo 和 git 还挺有趣的，如果你也想搭一个这样的网站，不用担心没有编程基础，网上找一个教程，花个一两天的时间可能就弄出来了，<s>还可以拿去跟朋友吹水</s>。</p>\n<p>现实不知道为什么开始在我的眼前变得割裂与破碎了，我每天坐在图书馆情绪低落的时候，已经不会再找到现实的朋友交流，或者说我一直没有这样的习惯，这也不是我的性格，我是一个现代斯多葛主义者，我对情绪的调整能力还是很强的，我也希望自己在朋友面前永远是开朗阳光的，所以我把自己阴暗的一面留在这里。好像说偏了，总之，相较于从现实寻求慰藉，我现在倒是喜欢在网上寻求价值和意义，尽管这在我之前看来非常荒谬。</p>\n<p>另外，我也有我追求的生活方式，比如数字游民的生活，一间独属于自己的房子，一个安静够大的书桌，我能不受干扰地做自己想做的事情，弹弹钢琴（现在还不会），写写代码，看看书，或者在阳台看着风景，晒着太阳发发呆，有时间跟朋友去到处玩，这就是我想要的生活方式，它很简单，它真的很吸引我。</p>\n<p>尼采曾经说过：</p>\n<blockquote>\n<p>一个人知道自己为什么而活，就可以忍受任何一种生活</p>\n</blockquote>\n<p>那我现在的生活呢？其实我现在的生活也已经很接近高中渴望的生活了，大学再怎么恶心，也确实给了很多自由的空间，比起高中的硬核时间表和无止息的刷题，我现在有大量的时间去实现我的想法，做我想做的事情。</p>\n<p>那么回到这个话题上，我为什么要搭一个博客呢，更多还是受前辈的启发吧，我从前辈的博客记录里面学到了很多东西，所以我在想我现在也写点东西，尽管不是技术类的，也许也可以帮助后来的人<strong>总之，我希望我的博客能激励你追求自己的梦想，给你带来启发，尽管在现在我的故事还刚刚开始，无妨，我相信自己会成为自己期待的样子，也希望你也有勇气去成为更好的自己。</strong></p>\n",
            "tags": [
                "随笔",
                "随笔"
            ]
        },
        {
            "id": "https://stoic-yang.github.io/2024/11/03/%E5%A4%8D%E6%B4%BB/",
            "url": "https://stoic-yang.github.io/2024/11/03/%E5%A4%8D%E6%B4%BB/",
            "title": "复活",
            "date_published": "2024-11-02T17:16:37.000Z",
            "content_html": "<pre><code>为什么叫复活呢？因为其实我在9月中旬的时候曾经搭过一次，但是我愚蠢地把网站公开到QQ动态了，我觉得个人博客这种东西还是跟自己现实的社交割裂比较好，不容易被重伤，写的时候能更加自由。\n\n    正经人谁写生活博客啊？写生活博客能叫正经人？\n</code></pre>\n",
            "tags": [
                "随笔",
                "生活",
                "随笔"
            ]
        },
        {
            "id": "https://stoic-yang.github.io/2024/11/03/hello-world/",
            "url": "https://stoic-yang.github.io/2024/11/03/hello-world/",
            "title": "Hello World",
            "date_published": "2024-11-02T16:07:49.037Z",
            "content_html": "<p>Welcome to <span class=\"exturl\" data-url=\"aHR0cHM6Ly9oZXhvLmlvLw==\">Hexo</span>! This is your very first post. Check <span class=\"exturl\" data-url=\"aHR0cHM6Ly9oZXhvLmlvL2RvY3Mv\">documentation</span> for more info. If you get any problems when using Hexo, you can find the answer in <span class=\"exturl\" data-url=\"aHR0cHM6Ly9oZXhvLmlvL2RvY3MvdHJvdWJsZXNob290aW5nLmh0bWw=\">troubleshooting</span> or you can ask me on <span class=\"exturl\" data-url=\"aHR0cHM6Ly9naXRodWIuY29tL2hleG9qcy9oZXhvL2lzc3Vlcw==\">GitHub</span>.</p>\n<h2 id=\"quick-start\"><a class=\"anchor\" href=\"#quick-start\">#</a> Quick Start</h2>\n<h3 id=\"create-a-new-post\"><a class=\"anchor\" href=\"#create-a-new-post\">#</a> Create a new post</h3>\n<p><figure class=\"highlight bash\"><table><tr><td class=\"gutter\"><pre><span class=\"line\">1</span><br></pre></td><td class=\"code\"><pre><span class=\"line\">$ hexo new <span class=\"string\">&quot;My New Post&quot;</span></span><br></pre></td></tr></table></figure></p>\n<p>More info: <span class=\"exturl\" data-url=\"aHR0cHM6Ly9oZXhvLmlvL2RvY3Mvd3JpdGluZy5odG1s\">Writing</span></p>\n<h3 id=\"run-server\"><a class=\"anchor\" href=\"#run-server\">#</a> Run server</h3>\n<p><figure class=\"highlight bash\"><table><tr><td class=\"gutter\"><pre><span class=\"line\">1</span><br></pre></td><td class=\"code\"><pre><span class=\"line\">$ hexo server</span><br></pre></td></tr></table></figure></p>\n<p>More info: <span class=\"exturl\" data-url=\"aHR0cHM6Ly9oZXhvLmlvL2RvY3Mvc2VydmVyLmh0bWw=\">Server</span></p>\n<h3 id=\"generate-static-files\"><a class=\"anchor\" href=\"#generate-static-files\">#</a> Generate static files</h3>\n<p><figure class=\"highlight bash\"><table><tr><td class=\"gutter\"><pre><span class=\"line\">1</span><br></pre></td><td class=\"code\"><pre><span class=\"line\">$ hexo generate</span><br></pre></td></tr></table></figure></p>\n<p>More info: <span class=\"exturl\" data-url=\"aHR0cHM6Ly9oZXhvLmlvL2RvY3MvZ2VuZXJhdGluZy5odG1s\">Generating</span></p>\n<h3 id=\"deploy-to-remote-sites\"><a class=\"anchor\" href=\"#deploy-to-remote-sites\">#</a> Deploy to remote sites</h3>\n<p><figure class=\"highlight bash\"><table><tr><td class=\"gutter\"><pre><span class=\"line\">1</span><br></pre></td><td class=\"code\"><pre><span class=\"line\">$ hexo deploy</span><br></pre></td></tr></table></figure></p>\n<p>More info: <span class=\"exturl\" data-url=\"aHR0cHM6Ly9oZXhvLmlvL2RvY3Mvb25lLWNvbW1hbmQtZGVwbG95bWVudC5odG1s\">Deployment</span></p>\n",
            "tags": []
        }
    ]
}